LICENSE.txt
MANIFEST.in
README.md
setup.py
bin/wikilocalctrl.py
jk_mediawiki/LocalMediaWikisMgr.py
jk_mediawiki/MWManagementCtx.py
jk_mediawiki/MediaWikiDiskUsageInfo.py
jk_mediawiki/MediaWikiExtensionInfo.py
jk_mediawiki/MediaWikiLocalUserInstallationMgr.py
jk_mediawiki/MediaWikiLocalUserServiceMgr.py
jk_mediawiki/MediaWikiSkinInfo.py
jk_mediawiki/__init__.py
jk_mediawiki.egg-info/PKG-INFO
jk_mediawiki.egg-info/SOURCES.txt
jk_mediawiki.egg-info/dependency_links.txt
jk_mediawiki.egg-info/not-zip-safe
jk_mediawiki.egg-info/requires.txt
jk_mediawiki.egg-info/top_level.txt
jk_mediawiki/impl/AbstractProcessFilter.py
jk_mediawiki/impl/LocalWikiInstInfo.py
jk_mediawiki/impl/LocalWikiScanner.py
jk_mediawiki/impl/OSProcessProvider.py
jk_mediawiki/impl/ProcessFilter.py
jk_mediawiki/impl/ProcessProviderCache.py
jk_mediawiki/impl/Utils.py
jk_mediawiki/impl/WikiCronProcessFilter.py
jk_mediawiki/impl/WikiNGINXProcessFilter.py
jk_mediawiki/impl/WikiPHPProcessFilter.py
jk_mediawiki/impl/__init__.py
jk_mediawiki/impl/lang_support_php.py
jk_mediawiki/lsfile/MediaWikiLocalSettingsArrayAppend.py
jk_mediawiki/lsfile/MediaWikiLocalSettingsComplexVariableAssignment.py
jk_mediawiki/lsfile/MediaWikiLocalSettingsFile.py
jk_mediawiki/lsfile/MediaWikiLocalSettingsVariableAssignment.py
jk_mediawiki/lsfile/__init__.py