Metadata-Version: 2.1
Name: jk-mediawiki
Version: 0.2021.12.1
Summary: This module provides functions, classes and binaries to assist in working with MediaWiki installations.
Home-page: UNKNOWN
Author: Jürgen Knauth
Author-email: pubsrc@binary-overflow.de
License: Apache2
Keywords: mediawiki,mw,php
Platform: UNKNOWN
Classifier: Development Status :: 4 - Beta
Classifier: License :: OSI Approved :: Apache Software License
Classifier: Programming Language :: Python :: 3
